odoo/addons/crm_lead_code/README.rst
odoo/addons/crm_lead_code/__init__.py
odoo/addons/crm_lead_code/__manifest__.py
odoo/addons/crm_lead_code/data/lead_sequence.xml
odoo/addons/crm_lead_code/i18n/bg.po
odoo/addons/crm_lead_code/i18n/crm_lead_code.pot
odoo/addons/crm_lead_code/i18n/de.po
odoo/addons/crm_lead_code/i18n/es.po
odoo/addons/crm_lead_code/i18n/es_AR.po
odoo/addons/crm_lead_code/i18n/fr.po
odoo/addons/crm_lead_code/i18n/hr.po
odoo/addons/crm_lead_code/i18n/it.po
odoo/addons/crm_lead_code/i18n/pt_BR.po
odoo/addons/crm_lead_code/i18n/sk.po
odoo/addons/crm_lead_code/i18n/sl.po
odoo/addons/crm_lead_code/i18n/tr.po
odoo/addons/crm_lead_code/i18n/zh_CN.po
odoo/addons/crm_lead_code/models/__init__.py
odoo/addons/crm_lead_code/models/crm_lead.py
odoo/addons/crm_lead_code/readme/CONTRIBUTORS.rst
odoo/addons/crm_lead_code/readme/DESCRIPTION.rst
odoo/addons/crm_lead_code/static/description/icon.png
odoo/addons/crm_lead_code/static/description/index.html
odoo/addons/crm_lead_code/tests/__init__.py
odoo/addons/crm_lead_code/tests/test_crm_lead_code.py
odoo/addons/crm_lead_code/views/crm_lead_view.xml
odoo14_addon_crm_lead_code-14.0.1.0.1.dev15.dist-info/METADATA
odoo14_addon_crm_lead_code-14.0.1.0.1.dev15.dist-info/WHEEL
odoo14_addon_crm_lead_code-14.0.1.0.1.dev15.dist-info/top_level.txt
odoo14_addon_crm_lead_code-14.0.1.0.1.dev15.dist-info/RECORD
